zenoh/__init__.py
zenoh/admin.py
zenoh/change.py
zenoh/data.py
zenoh/encoding.py
zenoh/exceptions.py
zenoh/logger.py
zenoh/path.py
zenoh/selector.py
zenoh/value.py
zenoh/workspace.py
zenoh/zenoh.py
zenoh/core/__init__.py
zenoh/core/timestamp.py
zenoh/core/zexception.py
zenoh/net/__init__.py
zenoh/net/binding.py
zenoh/net/converter.py
zenoh/net/session.py
zenoh-0.4.0.dist-info/LICENSE
zenoh-0.4.0.dist-info/METADATA
zenoh-0.4.0.dist-info/WHEEL
zenoh-0.4.0.dist-info/top_level.txt
zenoh-0.4.0.dist-info/RECORD
