Metadata-Version: 2.1
Name: zenoh
Version: 0.4.0
Summary: Python client API for zenoh
Home-page: https://github.com/atolab/zenoh-python
Author: kydos
License: UNKNOWN
Platform: UNKNOWN
Classifier: Programming Language :: Python :: 3
Classifier: Intended Audience :: Developers
Classifier: Development Status :: 4 - Beta
Classifier: Topic :: System :: Networking
Classifier: License :: OSI Approved :: Apache Software License
Classifier: License :: OSI Approved :: Eclipse Public License 2.0 (EPL-2.0)
Classifier: Operating System :: OS Independent
Requires-Dist: hexdump
Requires-Dist: mvar
Requires-Dist: papero (==0.2.7)
